syftr/README.md
syftr/__init__.py
syftr/agent_flows.py
syftr/amazon.py
syftr/analytics.py
syftr/api.py
syftr/baselines.py
syftr/cli.py
syftr/configuration.py
syftr/core.py
syftr/custom_metrics.py
syftr/event_loop.py
syftr/experiments.py
syftr/flows.py
syftr/helpers.py
syftr/hf_endpoint_embeddings.py
syftr/hf_endpoint_models.py
syftr/hierarchical_tpe.py
syftr/huggingface_helper.py
syftr/llm.py
syftr/logger.py
syftr/optimization.py
syftr/optuna_helper.py
syftr/patches.py
syftr/prompt_optimization.py
syftr/pruning.py
syftr/sota.py
syftr/startup.py
syftr/storage.py
syftr/studies.py
syftr/studyconfig_helper.py
syftr/templates.py
syftr/tracing.py
syftr/transfer_learning.py
syftr/validation.py
syftr/data/flows/silver_bullets.json
syftr/data/sota/sota_data.json
syftr/data/templates/agentic_templates.json
syftr/embeddings/__init__.py
syftr/embeddings/timeouts.py
syftr/evaluation/__init__.py
syftr/evaluation/evaluation.py
syftr/evaluation/evaluator_factory.py
syftr/instrumentation/__init__.py
syftr/instrumentation/arize.py
syftr/instrumentation/tokens.py
syftr/plotting/__init__.py
syftr/plotting/insights.py
syftr/plotting/optuna_plotting.py
syftr/ray/__init__.py
syftr/ray/runtime_env.py
syftr/ray/stop.py
syftr/ray/submit.py
syftr/ray/utils.py
syftr/readers/__init__.py
syftr/readers/html_file/__init__.py
syftr/readers/html_file/base.py
syftr/retrievers/__init__.py
syftr/retrievers/build.py
syftr/retrievers/storage.py
syftr/scripts/build_flow.py
syftr/scripts/build_retriever_flow.py
syftr/scripts/cancel_jobs.py
syftr/scripts/create_onnx.py
syftr/scripts/delete_study.py
syftr/scripts/gcp_anthropic.py
syftr/scripts/replace_models_pareto.py
syftr/scripts/rerun_incomplete.py
syftr/scripts/system_check.py
syftr/scripts/experiments/cerebras_mix.py
syftr/scripts/experiments/llm_judge_adherence.py
syftr/scripts/experiments/seeding.py
syftr/tuner/__init__.py
syftr/tuner/agent_tuner.py
syftr/tuner/core.py
syftr/tuner/qa_tuner.py
syftr/utils/__init__.py
syftr/utils/locks.py
syftr-0.3.0.dist-info/METADATA
syftr-0.3.0.dist-info/WHEEL
syftr-0.3.0.dist-info/entry_points.txt
syftr-0.3.0.dist-info/licenses/LICENSE
syftr-0.3.0.dist-info/RECORD
