Metadata-Version: 2.4
Name: syftr
Version: 0.3.0
Summary: syftr is an agent optimizer that helps you find the best agentic workflows for your budget.
Project-URL: Homepage, https://datarobot.com
Project-URL: Source, https://github.com/datarobot/syftr
Project-URL: Issues, https://github.com/datarobot/syftr/issues
License-Expression: MIT
License-File: LICENSE
Requires-Python: <3.13,>=3.11.1
Requires-Dist: adjusttext
Requires-Dist: aiolimiter
Requires-Dist: altair
Requires-Dist: arize-phoenix
Requires-Dist: boto3
Requires-Dist: botocore
Requires-Dist: click
Requires-Dist: cloudpickle
Requires-Dist: colorlog
Requires-Dist: dataframe-image
Requires-Dist: datasets>=3.3
Requires-Dist: diskcache
Requires-Dist: faiss-cpu
Requires-Dist: filelock
Requires-Dist: flock
Requires-Dist: fsspec
Requires-Dist: gitpython
Requires-Dist: google-cloud-aiplatform
Requires-Dist: html2text
Requires-Dist: huggingface-hub
Requires-Dist: ipdb
Requires-Dist: kaleido==0.2.1
Requires-Dist: kneed
Requires-Dist: langchain-community
Requires-Dist: langchain>0.3
Requires-Dist: llama-index
Requires-Dist: llama-index-agent-coa>=0.3.2
Requires-Dist: llama-index-agent-introspective
Requires-Dist: llama-index-agent-lats
Requires-Dist: llama-index-agent-openai
Requires-Dist: llama-index-callbacks-arize-phoenix
Requires-Dist: llama-index-cli
Requires-Dist: llama-index-core>=0.12.52
Requires-Dist: llama-index-embeddings-azure-openai
Requires-Dist: llama-index-embeddings-fastembed
Requires-Dist: llama-index-embeddings-huggingface
Requires-Dist: llama-index-embeddings-huggingface-optimum
Requires-Dist: llama-index-embeddings-openai
Requires-Dist: llama-index-embeddings-openai-like
Requires-Dist: llama-index-indices-managed-llama-cloud
Requires-Dist: llama-index-legacy
Requires-Dist: llama-index-llms-anthropic
Requires-Dist: llama-index-llms-azure-inference
Requires-Dist: llama-index-llms-azure-openai
Requires-Dist: llama-index-llms-cerebras
Requires-Dist: llama-index-llms-huggingface
Requires-Dist: llama-index-llms-ollama
Requires-Dist: llama-index-llms-openai
Requires-Dist: llama-index-llms-vertex==0.4.3
Requires-Dist: llama-index-llms-vllm
Requires-Dist: llama-index-multi-modal-llms-openai
Requires-Dist: llama-index-packs-agents-coa>=0.3.2
Requires-Dist: llama-index-program-openai
Requires-Dist: llama-index-question-gen-openai
Requires-Dist: llama-index-readers-file
Requires-Dist: llama-index-readers-llama-parse
Requires-Dist: llama-index-retrievers-bm25
Requires-Dist: llama-index-vector-stores-faiss
Requires-Dist: llama-index-vector-stores-qdrant
Requires-Dist: llvmlite>=0.44
Requires-Dist: lz4
Requires-Dist: maincontentextractor
Requires-Dist: numba>=0.60
Requires-Dist: numpy
Requires-Dist: openinference-instrumentation-llama-index==3.3.1
Requires-Dist: opentelemetry-exporter-otlp
Requires-Dist: opentelemetry-sdk
Requires-Dist: optimum[exporters]>=1.24.0
Requires-Dist: optuna==4.2.1
Requires-Dist: overrides
Requires-Dist: pals
Requires-Dist: pandas
Requires-Dist: paretoset
Requires-Dist: pip
Requires-Dist: plotly
Requires-Dist: psycopg2-binary
Requires-Dist: pydantic-file-secrets
Requires-Dist: pydantic-settings
Requires-Dist: python-dotenv
Requires-Dist: python-slugify
Requires-Dist: rapidfuzz
Requires-Dist: ray[client,data,default,serve,tune]==2.46.0
Requires-Dist: rich
Requires-Dist: rouge-score
Requires-Dist: s3fs
Requires-Dist: scikit-learn
Requires-Dist: seaborn
Requires-Dist: sentencepiece
Requires-Dist: sqlalchemy
Requires-Dist: statsmodels
Requires-Dist: tabulate
Requires-Dist: torch==2.7.0
Requires-Dist: trace-opt
Requires-Dist: transformers==4.48.3
Requires-Dist: tree-sitter
Requires-Dist: tree-sitter-language-pack>=0.7.3
Requires-Dist: tree-sitter-languages
Requires-Dist: types-protobuf
Requires-Dist: types-pytz
Requires-Dist: types-tabulate
Requires-Dist: uv-dynamic-versioning
Requires-Dist: vertexai==1.68.0
Provides-Extra: dev
Requires-Dist: altair; extra == 'dev'
Requires-Dist: ansible; extra == 'dev'
Requires-Dist: beautifulsoup4; extra == 'dev'
Requires-Dist: ipykernel; extra == 'dev'
Requires-Dist: ipython; extra == 'dev'
Requires-Dist: ipywidgets; extra == 'dev'
Requires-Dist: isort; extra == 'dev'
Requires-Dist: jupyter; extra == 'dev'
Requires-Dist: kneed; extra == 'dev'
Requires-Dist: matplotlib; extra == 'dev'
Requires-Dist: mypy; extra == 'dev'
Requires-Dist: nbformat; extra == 'dev'
Requires-Dist: nbstripout; extra == 'dev'
Requires-Dist: optuna-dashboard; extra == 'dev'
Requires-Dist: paretoset; extra == 'dev'
Requires-Dist: pre-commit; extra == 'dev'
Requires-Dist: py-irt; extra == 'dev'
Requires-Dist: pyro-ppl; extra == 'dev'
Requires-Dist: pytest-rerunfailures; extra == 'dev'
Requires-Dist: python-slugify; extra == 'dev'
Requires-Dist: pytz; extra == 'dev'
Requires-Dist: rpdb; extra == 'dev'
Requires-Dist: ruff; extra == 'dev'
Requires-Dist: scipy; extra == 'dev'
Requires-Dist: spacy; extra == 'dev'
Requires-Dist: types-python-slugify; extra == 'dev'
Requires-Dist: types-pyyaml; extra == 'dev'
Requires-Dist: types-requests; extra == 'dev'
Requires-Dist: types-tabulate; extra == 'dev'
Requires-Dist: xgboost; extra == 'dev'
Requires-Dist: yawsso; extra == 'dev'
